deepaigc/__init__.py
deepaigc-0.0.0.dist-info/METADATA
deepaigc-0.0.0.dist-info/WHEEL
deepaigc-0.0.0.dist-info/top_level.txt
deepaigc-0.0.0.dist-info/RECORD
