Metadata-Version: 2.1
Name: deepaigc
Version: 0.0.0
Summary: deepaigc
Home-page: https://www.aliyun.com
